simpsom_dask/__init__.py
simpsom_dask/decays.py
simpsom_dask/diagnostics.py
simpsom_dask/distances.py
simpsom_dask/neighborhoods.py
simpsom_dask/plots.py
simpsom_dask/simpsom.py
simpsom_dask/test_distances.py
simpsom_dask/tests.py
simpsom_dask/utils.py
simpsom_dask-1.0.3.dist-info/licenses/LICENSE
simpsom_dask-1.0.3.dist-info/METADATA
simpsom_dask-1.0.3.dist-info/WHEEL
simpsom_dask-1.0.3.dist-info/top_level.txt
simpsom_dask-1.0.3.dist-info/RECORD
