Metadata-Version: 2.4
Name: simpsom-dask
Version: 1.0.3
Summary: A mix of jcfaracco/xpysom-dask and fcomitani/simpsom, with heavy modifications
Author-email: Hugo Banderier <hugo.banderier@unibe.ch>
Project-URL: Homepage, https://github.com/hbanderier/simpsom-dask
Project-URL: Issues, https://github.com/hbanderier/simpsom-dask/issues
Classifier: Programming Language :: Python :: 3
Classifier: Operating System :: OS Independent
Classifier: License :: OSI Approved :: MIT License
Requires-Python: >=3.11
License-File: LICENSE
Requires-Dist: numpy
Requires-Dist: matplotlib
Requires-Dist: colormaps
Requires-Dist: scikit_learn
Requires-Dist: scipy
Requires-Dist: tqdm
Requires-Dist: dask>=2025.5.0
Requires-Dist: jupyter>=1.1.1
Requires-Dist: autoreload>=0.1.2
Requires-Dist: ipython>=9.2.0
Provides-Extra: daskml
Requires-Dist: dask; extra == "daskml"
Requires-Dist: dask_ml; extra == "daskml"
Provides-Extra: gpu
Requires-Dist: cupy; extra == "gpu"
Requires-Dist: cudf; extra == "gpu"
Dynamic: license-file
